datamart_nyu.py
datamart_nyu-0.2.5.dist-info/LICENSE.txt
datamart_nyu-0.2.5.dist-info/METADATA
datamart_nyu-0.2.5.dist-info/WHEEL
datamart_nyu-0.2.5.dist-info/top_level.txt
datamart_nyu-0.2.5.dist-info/RECORD
