Metadata-Version: 2.1
Name: datamart-nyu
Version: 0.2.5
Summary: Client library for NYU's DataMart system
Home-page: https://gitlab.com/ViDA-NYU/datamart/datamart-api
Author: Remi Rampin, Fernando Chirigati
Author-email: remi.rampin@nyu.edu, fchirigati@nyu.edu
Maintainer: Remi Rampin, Fernando Chirigati
Maintainer-email: remi.rampin@nyu.edu, fchirigati@nyu.edu
License: BSD-3-Clause
Project-URL: Homepage, https://gitlab.com/ViDA-NYU/datamart/datamart-api
Project-URL: Source, https://gitlab.com/ViDA-NYU/datamart/datamart-api
Project-URL: Tracker, https://gitlab.com/ViDA-NYU/datamart/datamart-api/issues
Keywords: datamart,rest,auctus
Platform: UNKNOWN
Classifier: Development Status :: 4 - Beta
Classifier: Intended Audience :: Science/Research
Classifier: Operating System :: OS Independent
Classifier: Programming Language :: Python :: 3
Classifier: Topic :: Internet :: WWW/HTTP :: Indexing/Search
Classifier: Topic :: Scientific/Engineering :: Information Analysis
Requires-Dist: datamart-rest (==0.2.5)
